getENA/__init__.py
getENA/getENA.py
getENA-1.2.2.data/scripts/getENA.py
getENA-1.2.2.dist-info/LICENSE
getENA-1.2.2.dist-info/METADATA
getENA-1.2.2.dist-info/WHEEL
getENA-1.2.2.dist-info/top_level.txt
getENA-1.2.2.dist-info/RECORD
